ramulator2/verilog_verification/sources/inlu_core.sv

/**
 * iNLU_core.sv
 * 
 * 核心创新一：iNLU (Integer Non-Linear Unit) 
 * 功能：在 PIM Bank 内部实现纯整型 Softmax 计算（指数部分）
 * 算法：多项式拟合 (Polynomial Approximation) - I-BERT 风格
 * 
 * 输入: i_data (INT32) - 缩放后的定点数 Logits
 * 输出: o_exp  (INT32) - 近似计算得到的 e^x * Scaling_Factor
 */

module inlu_core #(
    parameter int INT_WIDTH = 32
)(
    input  logic                 clk,
    input  logic                 rst_n,
    input  logic                 i_valid,
    input  logic [INT_WIDTH-1:0] i_data,    // 已减去最大值后的 Logits (均为负数或0)
    
    output logic                 o_valid,
    output logic [INT_WIDTH-1:0] o_exp      // 输出 e^x 的定点表示
);

    // --- 常数定义 (基于 I-BERT 算法，缩放比例为 2^10) ---
    // ln2 = 0.6931 * 1024 approx 710
    localparam logic [INT_WIDTH-1:0] LN2_INT = 32'd710;
    
    // 多项式系数 (ax + b)^2 + c
    // a = 0.3585 * 1024 = 367
    // b = 1.353 * 1024 = 1385
    // c = 0.344 * 1024 = 352
    localparam logic [INT_WIDTH-1:0] COEFF_A = 32'd367;
    localparam logic [INT_WIDTH-1:0] COEFF_B = 32'd1385;
    localparam logic [INT_WIDTH-1:0] COEFF_C = 32'd352;

    // --- 流水线寄存器 ---
    
    // Stage 1: 范围归约 (Range Reduction)
    // e^x = 2^n * e^f,  f = x - n*ln2,  f \in [-ln2, 0]
    logic [INT_WIDTH-1:0] n_reg;
    logic [INT_WIDTH-1:0] f_reg;
    logic                 v1_reg;
    
    // Stage 2: (f + b) 计算
    logic [INT_WIDTH-1:0] f_plus_b_reg;
    logic [INT_WIDTH-1:0] n2_reg;
    logic                 v2_reg;
    
    // Stage 3: (f + b)^2 计算 (乘法)
    logic [63:0]          f_plus_b_sq_reg;
    logic [INT_WIDTH-1:0] n3_reg;
    logic                 v3_reg;
    
    // Stage 4: a * (f + b)^2 + c 计算
    logic [INT_WIDTH-1:0] poly_result_reg;
    logic                 v4_reg;
    
    // --- 逻辑实现 ---

    // Stage 1: 范围归约
    always_ff @(posedge clk or negedge rst_n) begin
        if (!rst_n) begin
            n_reg  <= '0;
            f_reg  <= '0;
            v1_reg <= '0;
        end else if (i_valid) begin
            // n = floor(x / ln2)
            // 在硬件中，由于 x <= 0，可以使用简单的除法/近似
            // 这里为了演示使用有符号商计算
            n_reg  <= $signed(i_data) / $signed(LN2_INT);
            f_reg  <= $signed(i_data) % $signed(LN2_INT);
            v1_reg <= 1'b1;
        end else begin
            v1_reg <= 1'b0;
        end
    end

    // Stage 2: f + b
    always_ff @(posedge clk or negedge rst_n) begin
        if (!rst_n) begin
            f_plus_b_reg <= '0;
            n2_reg <= '0;
            v2_reg <= '0;
        end else if (v1_reg) begin
            f_plus_b_reg <= $signed(f_reg) + $signed(COEFF_B);
            n2_reg <= n_reg;
            v2_reg <= 1'b1;
        end else begin
            v2_reg <= 1'b0;
        end
    end

    // Stage 3: 平方
    always_ff @(posedge clk or negedge rst_n) begin
        if (!rst_n) begin
            f_plus_b_sq_reg <= '0;
            n3_reg <= '0;
            v3_reg <= '0;
        end else if (v2_reg) begin
            f_plus_b_sq_reg <= $signed(f_plus_b_reg) * $signed(f_plus_b_reg);
            n3_reg <= n2_reg;
            v3_reg <= 1'b1;
        end else begin
            v3_reg <= 1'b0;
        end
    end

    // Stage 4: a * poly + c 并应用 2^n (位移)
    always_ff @(posedge clk or negedge rst_n) begin
        if (!rst_n) begin
            poly_result_reg <= '0;
            v4_reg <= '0;
        end else if (v3_reg) begin
            // poly = (a * sq >> 20) + c
            // >> 20 是因为 f_plus_b_sq 带有双倍的缩放 (2^10 * 2^10)
            logic [63:0] temp_poly_full;
            temp_poly_full = ((64'(COEFF_A) * f_plus_b_sq_reg) >> 20) + 64'(COEFF_C);
            
            // 应用 2^n: 这里 n 通常为负数 (如 -1, -2...)
            if ($signed(n3_reg) <= 0) begin
                poly_result_reg <= temp_poly_full[31:0] >> (-$signed(n3_reg));
            end else begin
                poly_result_reg <= temp_poly_full[31:0] << $signed(n3_reg);
            end
            v4_reg <= 1'b1;
        end else begin
            v4_reg <= 1'b0;
        end
    end

    // 输出赋值
    assign o_valid = v4_reg;
    assign o_exp   = poly_result_reg;

endmodule

ramulator2/verilog_verification/inlu_waves.vcd
$version Generated by VerilatedVcd $end
$timescale 1ps $end
 $scope module TOP $end
  $var wire 1 1 clk $end
  $var wire 1 2 rst_n $end
  $var wire 1 3 i_valid $end
  $var wire 32 4 i_data [31:0] $end
  $var wire 1 5 o_valid $end
  $var wire 32 6 o_exp [31:0] $end
  $scope module inlu_core $end
   $var wire 32 7 INT_WIDTH [31:0] $end
   $var wire 1 1 clk $end
   $var wire 1 2 rst_n $end
   $var wire 1 3 i_valid $end
   $var wire 32 4 i_data [31:0] $end
   $var wire 1 5 o_valid $end
   $var wire 32 6 o_exp [31:0] $end
   $var wire 32 8 LN2_INT [31:0] $end
   $var wire 32 9 COEFF_A [31:0] $end
   $var wire 32 : COEFF_B [31:0] $end
   $var wire 32 ; COEFF_C [31:0] $end
   $var wire 32 # n_reg [31:0] $end
   $var wire 32 $ f_reg [31:0] $end
   $var wire 1 % v1_reg $end
   $var wire 32 & f_plus_b_reg [31:0] $end
   $var wire 32 ' n2_reg [31:0] $end
   $var wire 1 ( v2_reg $end
   $var wire 64 ) f_plus_b_sq_reg [63:0] $end
   $var wire 32 + n3_reg [31:0] $end
   $var wire 1 , v3_reg $end
   $var wire 32 - poly_result_reg [31:0] $end
   $var wire 1 . v4_reg $end
   $scope module unnamedblk1 $end
    $var wire 64 / temp_poly_full [63:0] $end
   $upscope $end
  $upscope $end
 $upscope $end
$enddefinitions $end


#0
b00000000000000000000000000000000 #
b00000000000000000000000000000000 $
0%
b00000000000000000000000000000000 &
b00000000000000000000000000000000 '
0(
b0000000000000000000000000000000000000000000000000000000000000000 )
b00000000000000000000000000000000 +
0,
b00000000000000000000000000000000 -
0.
b0000000000000000000000000000000000000000000000000000000000000000 /
01
02
03
b00000000000000000000000000000000 4
05
b00000000000000000000000000000000 6
b00000000000000000000000000100000 7
b00000000000000000000001011000110 8
b00000000000000000000000101101111 9
b00000000000000000000010101101001 :
b00000000000000000000000101100000 ;
#1
#2
#3
#4
#5
11
#6
#7
#8
#9
#10
01
#11
#12
#13
#14
#15
11
#16
#17
#18
#19
#20
01
#21
12
#22
#23
#24
#25
11
#26
#27
#28
#29
#30
01
13
#31
#32
#33
#34
#35
1%
11
#36
#37
#38
#39
#40
01
b11111111111111111111110100111010 4
#41
#42
#43
#44
#45
b11111111111111111111111111111111 #
b00000000000000000000010101101001 &
1(
11
#46
#47
#48
#49
#50
01
b11111111111111111111110000000000 4
#51
#52
#53
#54
#55
b11111111111111111111111011000110 $
b11111111111111111111111111111111 '
b0000000000000000000000000000000000000000000111010100010100010001 )
1,
11
#56
#57
#58
#59
#60
01
03
#61
#62
#63
#64
#65
0%
b00000000000000000000010000101111 &
b11111111111111111111111111111111 +
b00000000000000000000001111111111 -
1.
b0000000000000000000000000000000000000000000000000000001111111111 /
11
15
b00000000000000000000001111111111 6
#66
#67
#68
#69
#70
01
#71
#72
#73
#74
#75
0(
b0000000000000000000000000000000000000000000100011000000010100001 )
b00000000000000000000000111111111 -
11
b00000000000000000000000111111111 6
#76
#77
#78
#79
#80
01
#81
#82
#83
#84
#85
0,
b00000000000000000000000101111000 -
b0000000000000000000000000000000000000000000000000000001011110001 /
11
b00000000000000000000000101111000 6
#86
#87
#88
#89
#90
01
#91
#92
#93
#94
#95
0.
11
05
